{
  "updatedAt": "2026-06-26T06:44:49.023Z",
  "piped": [
    {
      "url": "https://piped.video/api",
      "latency": 257
    },
    {
      "url": "https://api.piped.projectsegfau.lt",
      "latency": 824
    },
    {
      "url": "https://api.piped.private.coffee",
      "latency": 863
    }
  ],
  "invidious": [
    {
      "url": "https://yewtu.be",
      "latency": 780
    },
    {
      "url": "https://invidious.tiekoetter.com",
      "latency": 913
    },
    {
      "url": "https://invidious.flokinet.to",
      "latency": 937
    }
  ],
  "cobalt": [],
  "stats": {
    "pipedTotal": 16,
    "pipedWorking": 3,
    "invidiousTotal": 21,
    "invidiousWorking": 3,
    "cobaltTotal": 4,
    "cobaltWorking": 0
  }
}